pytest_svn.py
pytest_svn-1.8.0.dist-info/LICENSE
pytest_svn-1.8.0.dist-info/METADATA
pytest_svn-1.8.0.dist-info/WHEEL
pytest_svn-1.8.0.dist-info/entry_points.txt
pytest_svn-1.8.0.dist-info/top_level.txt
pytest_svn-1.8.0.dist-info/RECORD
